stitches/__init__.py
stitches/_version.py
stitches/fx_data.py
stitches/fx_match.py
stitches/fx_pangeo.py
stitches/fx_processing.py
stitches/fx_recipe.py
stitches/fx_stitch.py
stitches/fx_util.py
stitches/generate_package_data.py
stitches/install_pkgdata.py
stitches/make_matching_archive.py
stitches/make_pangeo_table.py
stitches/make_tas_archive.py
stitches/package_data.py
stitches/data/__init__.py
stitches/data/example/test-archive_dat.csv
stitches/data/example/test-match.csv
stitches/data/example/test-match_dat.csv
stitches/data/example/test-match_w_dup.csv
stitches/data/example/test-recipe_dat.csv
stitches/data/example/test-target_dat.csv
stitches/data/tas-data/README.md
stitches/data/temp-data/README.md
stitches_emulator-0.12.3.dist-info/LICENSE
stitches_emulator-0.12.3.dist-info/METADATA
stitches_emulator-0.12.3.dist-info/WHEEL
stitches_emulator-0.12.3.dist-info/top_level.txt
stitches_emulator-0.12.3.dist-info/RECORD
